{
  "auth": {
    "user_pool_id": "us-east-1_GaVlP9jmn",
    "aws_region": "us-east-1",
    "user_pool_client_id": "77ta0lv36b9mot86kvv05jmsf7",
    "identity_pool_id": "us-east-1:91a9cfc6-8970-4746-a1f0-1d4c370a86f7",
    "mfa_methods": [],
    "standard_required_attributes": [
      "email"
    ],
    "username_attributes": [
      "email"
    ],
    "user_verification_types": [
      "email"
    ],
    "groups": [],
    "mfa_configuration": "NONE",
    "password_policy": {
      "min_length": 8,
      "require_lowercase": true,
      "require_numbers": true,
      "require_symbols": true,
      "require_uppercase": true
    },
    "unauthenticated_identities_enabled": true
  },
  "data": {
    "url": "https://ftvqoxwphvcbbksemwuzoqbgqu.appsync-api.us-east-1.amazonaws.com/graphql",
    "aws_region": "us-east-1",
    "default_authorization_type": "AMAZON_COGNITO_USER_POOLS",
    "authorization_types": [
      "AWS_IAM"
    ],
    "model_introspection": {
      "version": 1,
      "models": {
        "Url": {
          "name": "Url",
          "fields": {
            "id": {
              "name": "id",
              "isArray": false,
              "type": "ID",
              "isRequired": true,
              "attributes": []
            },
            "shortCode": {
              "name": "shortCode",
              "isArray": false,
              "type": "String",
              "isRequired": true,
              "attributes": []
            },
            "originalUrl": {
              "name": "originalUrl",
              "isArray": false,
              "type": "AWSURL",
              "isRequired": true,
              "attributes": []
            },
            "createdAt": {
              "name": "createdAt",
              "isArray": false,
              "type": "AWSDateTime",
              "isRequired": false,
              "attributes": []
            },
            "updatedAt": {
              "name": "updatedAt",
              "isArray": false,
              "type": "AWSDateTime",
              "isRequired": false,
              "attributes": [],
              "isReadOnly": true
            }
          },
          "syncable": true,
          "pluralName": "Urls",
          "attributes": [
            {
              "type": "model",
              "properties": {}
            },
            {
              "type": "auth",
              "properties": {
                "rules": [
                  {
                    "provider": "userPools",
                    "ownerField": "owner",
                    "allow": "owner",
                    "identityClaim": "cognito:username",
                    "operations": [
                      "create",
                      "update",
                      "delete",
                      "read"
                    ]
                  }
                ]
              }
            }
          ],
          "primaryKeyInfo": {
            "isCustomPrimaryKey": false,
            "primaryKeyFieldName": "id",
            "sortKeyFieldNames": []
          }
        }
      },
      "enums": {},
      "nonModels": {}
    }
  },
  "version": "1.4",
  "custom": {
    "API": {
      "URL Shortener API": {
        "endpoint": "https://9oe4um4du5.execute-api.us-east-1.amazonaws.com/prod/",
        "region": "us-east-1",
        "apiName": "URL Shortener API"
      }
    }
  }
}